{
  "_schema": "device-knowledge/2.0",
  "_type": "normal_ic",
  "_layers": [
    "L0_skeleton",
    "L1_electrical"
  ],
  "mpn": "AMS3431",
  "manufacturer": "Advanced Monolithic Systems",
  "category": "Other",
  "description": "PRECISION ADJUSTABLE SHUNT REGULATOR",
  "packages": {
    "TO-92": {
      "pin_count": 3,
      "pins": {
        "1": {
          "name": "CATHODE",
          "direction": "BIDIRECTIONAL",
          "signal_type": "ANALOG",
          "description": "Shunt regulator cathode and regulated output terminal",
          "unused_treatment": null
        },
        "2": {
          "name": "ANODE",
          "direction": "POWER_IN",
          "signal_type": "POWER",
          "description": "Shunt regulator anode and ground reference",
          "unused_treatment": null
        },
        "3": {
          "name": "REF",
          "direction": "INPUT",
          "signal_type": "ANALOG",
          "description": "Reference input for setting the output voltage",
          "unused_treatment": null
        }
      }
    },
    "3L SOT-23": {
      "pin_count": 3,
      "pins": {
        "1": {
          "name": "CATHODE",
          "direction": "BIDIRECTIONAL",
          "signal_type": "ANALOG",
          "description": "Shunt regulator cathode and regulated output terminal",
          "unused_treatment": null
        },
        "3": {
          "name": "ANODE",
          "direction": "POWER_IN",
          "signal_type": "POWER",
          "description": "Shunt regulator anode and ground reference",
          "unused_treatment": null
        },
        "2": {
          "name": "REF",
          "direction": "INPUT",
          "signal_type": "ANALOG",
          "description": "Reference input for setting the output voltage",
          "unused_treatment": null
        }
      }
    }
  },
  "absolute_maximum_ratings": {
    "VZ": {
      "parameter": "Cathode Voltage",
      "min": null,
      "max": 37,
      "unit": "V",
      "conditions": null
    },
    "IZ": {
      "parameter": "Continuous Cathode Current",
      "min": -10,
      "max": 150,
      "unit": "mA",
      "conditions": null
    },
    "IREF": {
      "parameter": "Reference Input Current",
      "min": null,
      "max": 10,
      "unit": "mA",
      "conditions": null
    },
    "TJ": {
      "parameter": "Junction Temperature",
      "min": -40,
      "max": 125,
      "unit": "°C",
      "conditions": null
    },
    "PD": {
      "parameter": "Internal Power Dissipation",
      "min": null,
      "max": 0.78,
      "unit": "W",
      "conditions": "TO-92 Package"
    },
    "PD_SOT_23_Package": {
      "parameter": "Internal Power Dissipation",
      "min": null,
      "max": 0.28,
      "unit": "W",
      "conditions": "SOT-23 Package"
    },
    "θJA": {
      "parameter": "Thermal Resistance",
      "min": null,
      "max": 160,
      "unit": "°C/W",
      "conditions": "TO-92 Package"
    },
    "θJA_SOT_23_Package": {
      "parameter": "Thermal Resistance",
      "min": null,
      "max": 410,
      "unit": "°C/W",
      "conditions": "SOT-23 Package"
    }
  },
  "electrical_parameters": {
    "VREF": {
      "parameter": "Reference Voltage",
      "min": 2.489,
      "typ": 2.495,
      "max": 2.501,
      "unit": "V",
      "conditions": "IZ=10 mA, TA = +25°C"
    },
    "VREF_IZ_10_mA__TA____25_C": {
      "parameter": "Reference Voltage",
      "min": 2.47,
      "typ": 2.495,
      "max": 2.52,
      "unit": "V",
      "conditions": "IZ=10 mA, TA = +25°C"
    },
    "IREF": {
      "parameter": "Reference Input Current",
      "min": null,
      "typ": 0.5,
      "max": 4.0,
      "unit": "µA",
      "conditions": "R1 = 10kΩ, R2 = ∞ (test circuit 2)"
    },
    "IREF_R1___10k___R2______test_circui": {
      "parameter": "Reference Input Current",
      "min": null,
      "typ": 0.5,
      "max": 4.0,
      "unit": "µA",
      "conditions": "R1 = 10kΩ, R2 = ∞ (test circuit 2)"
    },
    "IZ(off)": {
      "parameter": "Off State Cathode Current",
      "min": null,
      "typ": 0.04,
      "max": 0.5,
      "unit": "µA",
      "conditions": "VZ = 36V, VREF = 0V (test circuit 3)"
    },
    "IZ(off)_VZ___36V__VREF___0V__test_circ": {
      "parameter": "Off State Cathode Current",
      "min": null,
      "typ": 0.04,
      "max": 0.5,
      "unit": "µA",
      "conditions": "VZ = 36V, VREF = 0V (test circuit 3)"
    },
    "|ZKA|": {
      "parameter": "Dynamic Output Impedance",
      "min": null,
      "typ": 0.25,
      "max": 0.5,
      "unit": "Ω",
      "conditions": "f < 1KHz, VZ = VREF, IZ = 100µA to 100mA (test circuit 1)"
    },
    "|ZKA|_f___1KHz__VZ___VREF__IZ___100": {
      "parameter": "Dynamic Output Impedance",
      "min": null,
      "typ": 0.25,
      "max": 0.5,
      "unit": "Ω",
      "conditions": "f < 1KHz, VZ = VREF, IZ = 100µA to 100mA (test circuit 1)"
    },
    "IZ(min)": {
      "parameter": "Minimum Operating Current",
      "min": null,
      "typ": 100,
      "max": 250,
      "unit": "µA",
      "conditions": "VZ = VREF (test circuit 1)"
    },
    "IZ(min)_VZ___VREF__test_circuit_1": {
      "parameter": "Minimum Operating Current",
      "min": null,
      "typ": 100,
      "max": 250,
      "unit": "µA",
      "conditions": "VZ = VREF (test circuit 1)"
    }
  },
  "drc_hints": {
    "vref": {
      "min": 2.489,
      "typ": 2.495,
      "max": 2.501,
      "unit": "V"
    }
  },
  "thermal": {
    "power_dissipation": {
      "parameter": "Internal Power Dissipation",
      "symbol": "PD",
      "min": null,
      "typ": null,
      "max": 0.78,
      "value": null,
      "unit": "W",
      "conditions": "TO-92 Package",
      "source": "absolute_maximum_ratings"
    },
    "power_dissipation_SOT_23_Package": {
      "parameter": "Internal Power Dissipation",
      "symbol": "PD",
      "min": null,
      "typ": null,
      "max": 0.28,
      "value": null,
      "unit": "W",
      "conditions": "SOT-23 Package",
      "source": "absolute_maximum_ratings"
    },
    "theta_ja": {
      "parameter": "Thermal Resistance",
      "symbol": "θJA",
      "min": null,
      "typ": null,
      "max": 160,
      "value": null,
      "unit": "°C/W",
      "conditions": "TO-92 Package",
      "source": "absolute_maximum_ratings"
    },
    "theta_ja_SOT_23_Package": {
      "parameter": "Thermal Resistance",
      "symbol": "θJA",
      "min": null,
      "typ": null,
      "max": 410,
      "value": null,
      "unit": "°C/W",
      "conditions": "SOT-23 Package",
      "source": "absolute_maximum_ratings"
    }
  },
  "domains": {
    "pin": {
      "packages": {
        "TO-92": {
          "pin_count": 3,
          "pins": {
            "1": {
              "name": "CATHODE",
              "direction": "BIDIRECTIONAL",
              "signal_type": "ANALOG",
              "description": "Shunt regulator cathode and regulated output terminal",
              "unused_treatment": null
            },
            "2": {
              "name": "ANODE",
              "direction": "POWER_IN",
              "signal_type": "POWER",
              "description": "Shunt regulator anode and ground reference",
              "unused_treatment": null
            },
            "3": {
              "name": "REF",
              "direction": "INPUT",
              "signal_type": "ANALOG",
              "description": "Reference input for setting the output voltage",
              "unused_treatment": null
            }
          }
        },
        "3L SOT-23": {
          "pin_count": 3,
          "pins": {
            "1": {
              "name": "CATHODE",
              "direction": "BIDIRECTIONAL",
              "signal_type": "ANALOG",
              "description": "Shunt regulator cathode and regulated output terminal",
              "unused_treatment": null
            },
            "3": {
              "name": "ANODE",
              "direction": "POWER_IN",
              "signal_type": "POWER",
              "description": "Shunt regulator anode and ground reference",
              "unused_treatment": null
            },
            "2": {
              "name": "REF",
              "direction": "INPUT",
              "signal_type": "ANALOG",
              "description": "Reference input for setting the output voltage",
              "unused_treatment": null
            }
          }
        }
      }
    },
    "electrical": {
      "absolute_maximum_ratings": {
        "VZ": {
          "parameter": "Cathode Voltage",
          "min": null,
          "max": 37,
          "unit": "V",
          "conditions": null
        },
        "IZ": {
          "parameter": "Continuous Cathode Current",
          "min": -10,
          "max": 150,
          "unit": "mA",
          "conditions": null
        },
        "IREF": {
          "parameter": "Reference Input Current",
          "min": null,
          "max": 10,
          "unit": "mA",
          "conditions": null
        },
        "TJ": {
          "parameter": "Junction Temperature",
          "min": -40,
          "max": 125,
          "unit": "°C",
          "conditions": null
        },
        "PD": {
          "parameter": "Internal Power Dissipation",
          "min": null,
          "max": 0.78,
          "unit": "W",
          "conditions": "TO-92 Package"
        },
        "PD_SOT_23_Package": {
          "parameter": "Internal Power Dissipation",
          "min": null,
          "max": 0.28,
          "unit": "W",
          "conditions": "SOT-23 Package"
        },
        "θJA": {
          "parameter": "Thermal Resistance",
          "min": null,
          "max": 160,
          "unit": "°C/W",
          "conditions": "TO-92 Package"
        },
        "θJA_SOT_23_Package": {
          "parameter": "Thermal Resistance",
          "min": null,
          "max": 410,
          "unit": "°C/W",
          "conditions": "SOT-23 Package"
        }
      },
      "electrical_parameters": {
        "VREF": {
          "parameter": "Reference Voltage",
          "min": 2.489,
          "typ": 2.495,
          "max": 2.501,
          "unit": "V",
          "conditions": "IZ=10 mA, TA = +25°C"
        },
        "VREF_IZ_10_mA__TA____25_C": {
          "parameter": "Reference Voltage",
          "min": 2.47,
          "typ": 2.495,
          "max": 2.52,
          "unit": "V",
          "conditions": "IZ=10 mA, TA = +25°C"
        },
        "IREF": {
          "parameter": "Reference Input Current",
          "min": null,
          "typ": 0.5,
          "max": 4.0,
          "unit": "µA",
          "conditions": "R1 = 10kΩ, R2 = ∞ (test circuit 2)"
        },
        "IREF_R1___10k___R2______test_circui": {
          "parameter": "Reference Input Current",
          "min": null,
          "typ": 0.5,
          "max": 4.0,
          "unit": "µA",
          "conditions": "R1 = 10kΩ, R2 = ∞ (test circuit 2)"
        },
        "IZ(off)": {
          "parameter": "Off State Cathode Current",
          "min": null,
          "typ": 0.04,
          "max": 0.5,
          "unit": "µA",
          "conditions": "VZ = 36V, VREF = 0V (test circuit 3)"
        },
        "IZ(off)_VZ___36V__VREF___0V__test_circ": {
          "parameter": "Off State Cathode Current",
          "min": null,
          "typ": 0.04,
          "max": 0.5,
          "unit": "µA",
          "conditions": "VZ = 36V, VREF = 0V (test circuit 3)"
        },
        "|ZKA|": {
          "parameter": "Dynamic Output Impedance",
          "min": null,
          "typ": 0.25,
          "max": 0.5,
          "unit": "Ω",
          "conditions": "f < 1KHz, VZ = VREF, IZ = 100µA to 100mA (test circuit 1)"
        },
        "|ZKA|_f___1KHz__VZ___VREF__IZ___100": {
          "parameter": "Dynamic Output Impedance",
          "min": null,
          "typ": 0.25,
          "max": 0.5,
          "unit": "Ω",
          "conditions": "f < 1KHz, VZ = VREF, IZ = 100µA to 100mA (test circuit 1)"
        },
        "IZ(min)": {
          "parameter": "Minimum Operating Current",
          "min": null,
          "typ": 100,
          "max": 250,
          "unit": "µA",
          "conditions": "VZ = VREF (test circuit 1)"
        },
        "IZ(min)_VZ___VREF__test_circuit_1": {
          "parameter": "Minimum Operating Current",
          "min": null,
          "typ": 100,
          "max": 250,
          "unit": "µA",
          "conditions": "VZ = VREF (test circuit 1)"
        }
      },
      "drc_hints": {
        "vref": {
          "min": 2.489,
          "typ": 2.495,
          "max": 2.501,
          "unit": "V"
        }
      }
    },
    "thermal": {
      "power_dissipation": {
        "parameter": "Internal Power Dissipation",
        "symbol": "PD",
        "min": null,
        "typ": null,
        "max": 0.78,
        "value": null,
        "unit": "W",
        "conditions": "TO-92 Package",
        "source": "absolute_maximum_ratings"
      },
      "power_dissipation_SOT_23_Package": {
        "parameter": "Internal Power Dissipation",
        "symbol": "PD",
        "min": null,
        "typ": null,
        "max": 0.28,
        "value": null,
        "unit": "W",
        "conditions": "SOT-23 Package",
        "source": "absolute_maximum_ratings"
      },
      "theta_ja": {
        "parameter": "Thermal Resistance",
        "symbol": "θJA",
        "min": null,
        "typ": null,
        "max": 160,
        "value": null,
        "unit": "°C/W",
        "conditions": "TO-92 Package",
        "source": "absolute_maximum_ratings"
      },
      "theta_ja_SOT_23_Package": {
        "parameter": "Thermal Resistance",
        "symbol": "θJA",
        "min": null,
        "typ": null,
        "max": 410,
        "value": null,
        "unit": "°C/W",
        "conditions": "SOT-23 Package",
        "source": "absolute_maximum_ratings"
      }
    }
  }
}
