{
  "_schema": "sch-review-device/1.1",
  "_type": "normal_ic",
  "_layers": [
    "L0_skeleton",
    "L1_electrical"
  ],
  "mpn": "SGM8051/SGM8052/SGM8053/SGM8054/SGM8055",
  "manufacturer": "SG Micro",
  "category": "OpAmp",
  "description": "250MHz, Rail-to-Rail Output, CMOS Operational Amplifiers",
  "packages": {
    "SOT-23-5": {
      "pin_count": 5,
      "pins": {
        "5": {
          "name": "+Vs",
          "direction": "POWER_IN",
          "signal_type": "POWER",
          "description": "Positive power supply",
          "unused_treatment": null
        },
        "2": {
          "name": "-Vs",
          "direction": "POWER_IN",
          "signal_type": "POWER",
          "description": "Negative power supply",
          "unused_treatment": null
        },
        "3": {
          "name": "+IN",
          "direction": "INPUT",
          "signal_type": "ANALOG",
          "description": "Non-inverting input (single channel)",
          "unused_treatment": null
        },
        "4": {
          "name": "-IN",
          "direction": "INPUT",
          "signal_type": "ANALOG",
          "description": "Inverting input (single channel)",
          "unused_treatment": null
        },
        "1": {
          "name": "OUT",
          "direction": "OUTPUT",
          "signal_type": "ANALOG",
          "description": "Output (single channel)",
          "unused_treatment": null
        }
      }
    },
    "SOT-23-6": {
      "pin_count": 6,
      "pins": {
        "6": {
          "name": "+Vs",
          "direction": "POWER_IN",
          "signal_type": "POWER",
          "description": "Positive power supply",
          "unused_treatment": null
        },
        "2": {
          "name": "-Vs",
          "direction": "POWER_IN",
          "signal_type": "POWER",
          "description": "Negative power supply",
          "unused_treatment": null
        },
        "3": {
          "name": "+IN",
          "direction": "INPUT",
          "signal_type": "ANALOG",
          "description": "Non-inverting input (single channel)",
          "unused_treatment": null
        },
        "4": {
          "name": "-IN",
          "direction": "INPUT",
          "signal_type": "ANALOG",
          "description": "Inverting input (single channel)",
          "unused_treatment": null
        },
        "1": {
          "name": "OUT",
          "direction": "OUTPUT",
          "signal_type": "ANALOG",
          "description": "Output (single channel)",
          "unused_treatment": null
        },
        "5": {
          "name": "DISABLE",
          "direction": "INPUT",
          "signal_type": "DIGITAL",
          "description": "Shutdown control input",
          "unused_treatment": null
        }
      }
    },
    "SOIC-8": {
      "pin_count": 8,
      "pins": {
        "7": {
          "name": "+Vs",
          "direction": "POWER_IN",
          "signal_type": "POWER",
          "description": "Positive power supply (also: OUTB — Output, channel B)",
          "unused_treatment": null
        },
        "8": {
          "name": "+Vs",
          "direction": "POWER_IN",
          "signal_type": "POWER",
          "description": "Positive power supply (also: DISABLE — Shutdown control input) (also: NC — No internal connection)",
          "unused_treatment": null
        },
        "4": {
          "name": "-Vs",
          "direction": "POWER_IN",
          "signal_type": "POWER",
          "description": "Negative power supply",
          "unused_treatment": null
        },
        "3": {
          "name": "+IN",
          "direction": "INPUT",
          "signal_type": "ANALOG",
          "description": "Non-inverting input (single channel) (also: +INA — Non-inverting input, channel A)",
          "unused_treatment": null
        },
        "2": {
          "name": "-IN",
          "direction": "INPUT",
          "signal_type": "ANALOG",
          "description": "Inverting input (single channel) (also: -INA — Inverting input, channel A)",
          "unused_treatment": null
        },
        "6": {
          "name": "OUT",
          "direction": "OUTPUT",
          "signal_type": "ANALOG",
          "description": "Output (single channel) (also: -INB — Inverting input, channel B)",
          "unused_treatment": null
        },
        "1": {
          "name": "OUTA",
          "direction": "OUTPUT",
          "signal_type": "ANALOG",
          "description": "Output, channel A (also: NC — No internal connection)",
          "unused_treatment": null
        },
        "5": {
          "name": "+INB",
          "direction": "INPUT",
          "signal_type": "ANALOG",
          "description": "Non-inverting input, channel B (also: NC — No internal connection)",
          "unused_treatment": null
        }
      }
    },
    "MSOP-8": {
      "pin_count": 8,
      "pins": {
        "8": {
          "name": "+Vs",
          "direction": "POWER_IN",
          "signal_type": "POWER",
          "description": "Positive power supply",
          "unused_treatment": null
        },
        "4": {
          "name": "-Vs",
          "direction": "POWER_IN",
          "signal_type": "POWER",
          "description": "Negative power supply",
          "unused_treatment": null
        },
        "3": {
          "name": "+INA",
          "direction": "INPUT",
          "signal_type": "ANALOG",
          "description": "Non-inverting input, channel A",
          "unused_treatment": null
        },
        "2": {
          "name": "-INA",
          "direction": "INPUT",
          "signal_type": "ANALOG",
          "description": "Inverting input, channel A",
          "unused_treatment": null
        },
        "1": {
          "name": "OUTA",
          "direction": "OUTPUT",
          "signal_type": "ANALOG",
          "description": "Output, channel A",
          "unused_treatment": null
        },
        "5": {
          "name": "+INB",
          "direction": "INPUT",
          "signal_type": "ANALOG",
          "description": "Non-inverting input, channel B",
          "unused_treatment": null
        },
        "6": {
          "name": "-INB",
          "direction": "INPUT",
          "signal_type": "ANALOG",
          "description": "Inverting input, channel B",
          "unused_treatment": null
        },
        "7": {
          "name": "OUTB",
          "direction": "OUTPUT",
          "signal_type": "ANALOG",
          "description": "Output, channel B",
          "unused_treatment": null
        }
      }
    },
    "SOIC-14": {
      "pin_count": 14,
      "pins": {
        "4": {
          "name": "+Vs",
          "direction": "POWER_IN",
          "signal_type": "POWER",
          "description": "Positive power supply",
          "unused_treatment": null
        },
        "11": {
          "name": "-Vs",
          "direction": "POWER_IN",
          "signal_type": "POWER",
          "description": "Negative power supply",
          "unused_treatment": null
        },
        "3": {
          "name": "+INA",
          "direction": "INPUT",
          "signal_type": "ANALOG",
          "description": "Non-inverting input, channel A",
          "unused_treatment": null
        },
        "2": {
          "name": "-INA",
          "direction": "INPUT",
          "signal_type": "ANALOG",
          "description": "Inverting input, channel A",
          "unused_treatment": null
        },
        "1": {
          "name": "OUTA",
          "direction": "OUTPUT",
          "signal_type": "ANALOG",
          "description": "Output, channel A",
          "unused_treatment": null
        },
        "5": {
          "name": "+INB",
          "direction": "INPUT",
          "signal_type": "ANALOG",
          "description": "Non-inverting input, channel B",
          "unused_treatment": null
        },
        "6": {
          "name": "-INB",
          "direction": "INPUT",
          "signal_type": "ANALOG",
          "description": "Inverting input, channel B",
          "unused_treatment": null
        },
        "7": {
          "name": "OUTB",
          "direction": "OUTPUT",
          "signal_type": "ANALOG",
          "description": "Output, channel B",
          "unused_treatment": null
        },
        "10": {
          "name": "+INC",
          "direction": "INPUT",
          "signal_type": "ANALOG",
          "description": "Non-inverting input, channel C",
          "unused_treatment": null
        },
        "9": {
          "name": "-INC",
          "direction": "INPUT",
          "signal_type": "ANALOG",
          "description": "Inverting input, channel C",
          "unused_treatment": null
        },
        "8": {
          "name": "OUTC",
          "direction": "OUTPUT",
          "signal_type": "ANALOG",
          "description": "Output, channel C",
          "unused_treatment": null
        },
        "12": {
          "name": "+IND",
          "direction": "INPUT",
          "signal_type": "ANALOG",
          "description": "Non-inverting input, channel D",
          "unused_treatment": null
        },
        "13": {
          "name": "-IND",
          "direction": "INPUT",
          "signal_type": "ANALOG",
          "description": "Inverting input, channel D",
          "unused_treatment": null
        },
        "14": {
          "name": "OUTD",
          "direction": "OUTPUT",
          "signal_type": "ANALOG",
          "description": "Output, channel D",
          "unused_treatment": null
        }
      }
    },
    "TSSOP-14": {
      "pin_count": 14,
      "pins": {
        "4": {
          "name": "+Vs",
          "direction": "POWER_IN",
          "signal_type": "POWER",
          "description": "Positive power supply",
          "unused_treatment": null
        },
        "11": {
          "name": "-Vs",
          "direction": "POWER_IN",
          "signal_type": "POWER",
          "description": "Negative power supply",
          "unused_treatment": null
        },
        "3": {
          "name": "+INA",
          "direction": "INPUT",
          "signal_type": "ANALOG",
          "description": "Non-inverting input, channel A",
          "unused_treatment": null
        },
        "2": {
          "name": "-INA",
          "direction": "INPUT",
          "signal_type": "ANALOG",
          "description": "Inverting input, channel A",
          "unused_treatment": null
        },
        "1": {
          "name": "OUTA",
          "direction": "OUTPUT",
          "signal_type": "ANALOG",
          "description": "Output, channel A",
          "unused_treatment": null
        },
        "5": {
          "name": "+INB",
          "direction": "INPUT",
          "signal_type": "ANALOG",
          "description": "Non-inverting input, channel B",
          "unused_treatment": null
        },
        "6": {
          "name": "-INB",
          "direction": "INPUT",
          "signal_type": "ANALOG",
          "description": "Inverting input, channel B",
          "unused_treatment": null
        },
        "7": {
          "name": "OUTB",
          "direction": "OUTPUT",
          "signal_type": "ANALOG",
          "description": "Output, channel B",
          "unused_treatment": null
        },
        "10": {
          "name": "+INC",
          "direction": "INPUT",
          "signal_type": "ANALOG",
          "description": "Non-inverting input, channel C",
          "unused_treatment": null
        },
        "9": {
          "name": "-INC",
          "direction": "INPUT",
          "signal_type": "ANALOG",
          "description": "Inverting input, channel C",
          "unused_treatment": null
        },
        "8": {
          "name": "OUTC",
          "direction": "OUTPUT",
          "signal_type": "ANALOG",
          "description": "Output, channel C",
          "unused_treatment": null
        },
        "12": {
          "name": "+IND",
          "direction": "INPUT",
          "signal_type": "ANALOG",
          "description": "Non-inverting input, channel D",
          "unused_treatment": null
        },
        "13": {
          "name": "-IND",
          "direction": "INPUT",
          "signal_type": "ANALOG",
          "description": "Inverting input, channel D",
          "unused_treatment": null
        },
        "14": {
          "name": "OUTD",
          "direction": "OUTPUT",
          "signal_type": "ANALOG",
          "description": "Output, channel D",
          "unused_treatment": null
        }
      }
    },
    "MSOP-10": {
      "pin_count": 10,
      "pins": {
        "10": {
          "name": "+Vs",
          "direction": "POWER_IN",
          "signal_type": "POWER",
          "description": "Positive power supply",
          "unused_treatment": null
        },
        "4": {
          "name": "-Vs",
          "direction": "POWER_IN",
          "signal_type": "POWER",
          "description": "Negative power supply",
          "unused_treatment": null
        },
        "3": {
          "name": "+INA",
          "direction": "INPUT",
          "signal_type": "ANALOG",
          "description": "Non-inverting input, channel A",
          "unused_treatment": null
        },
        "2": {
          "name": "-INA",
          "direction": "INPUT",
          "signal_type": "ANALOG",
          "description": "Inverting input, channel A",
          "unused_treatment": null
        },
        "1": {
          "name": "OUTA",
          "direction": "OUTPUT",
          "signal_type": "ANALOG",
          "description": "Output, channel A",
          "unused_treatment": null
        },
        "7": {
          "name": "+INB",
          "direction": "INPUT",
          "signal_type": "ANALOG",
          "description": "Non-inverting input, channel B",
          "unused_treatment": null
        },
        "8": {
          "name": "-INB",
          "direction": "INPUT",
          "signal_type": "ANALOG",
          "description": "Inverting input, channel B",
          "unused_treatment": null
        },
        "9": {
          "name": "OUTB",
          "direction": "OUTPUT",
          "signal_type": "ANALOG",
          "description": "Output, channel B",
          "unused_treatment": null
        },
        "5": {
          "name": "DISABLE",
          "direction": "INPUT",
          "signal_type": "DIGITAL",
          "description": "Shutdown control input",
          "unused_treatment": null
        },
        "6": {
          "name": "DISABLE",
          "direction": "INPUT",
          "signal_type": "DIGITAL",
          "description": "Shutdown control input",
          "unused_treatment": null
        }
      }
    }
  },
  "absolute_maximum_ratings": {
    "Vs": {
      "parameter": "Supply Voltage",
      "min": null,
      "max": 6,
      "unit": "V",
      "conditions": null
    },
    "Vcm": {
      "parameter": "Input Common Mode Voltage Range",
      "min": null,
      "max": null,
      "unit": "V",
      "conditions": "(-Vs) - 0.1V to (+Vs) + 0.1V"
    },
    "θJA": {
      "parameter": "Package Thermal Resistance (SOT-23-5)",
      "min": null,
      "max": null,
      "unit": "°C/W",
      "conditions": "TA = +25°C"
    },
    "θJA_TA____25_C": {
      "parameter": "Package Thermal Resistance (MSOP-10)",
      "min": null,
      "max": null,
      "unit": "°C/W",
      "conditions": "TA = +25°C"
    },
    "TJ": {
      "parameter": "Junction Temperature",
      "min": null,
      "max": 150,
      "unit": "°C",
      "conditions": null
    },
    "Tstg": {
      "parameter": "Storage Temperature Range",
      "min": -65,
      "max": 150,
      "unit": "°C",
      "conditions": null
    }
  },
  "electrical_parameters": {
    "GBWP": {
      "parameter": "Gain-Bandwidth Product",
      "min": null,
      "typ": 90,
      "max": null,
      "unit": "MHz",
      "conditions": "G = +10, RL = 150Ω"
    },
    "GBWP_G____10__RL___1k": {
      "parameter": "Gain-Bandwidth Product",
      "min": null,
      "typ": 120,
      "max": null,
      "unit": "MHz",
      "conditions": "G = +10, RL = 1kΩ"
    },
    "SR": {
      "parameter": "Slew Rate",
      "min": null,
      "typ": 93,
      "max": null,
      "unit": "V/µs",
      "conditions": "G = +1, 2V output step"
    },
    "SR_G____2__2V_output_step": {
      "parameter": "Slew Rate",
      "min": null,
      "typ": 116,
      "max": null,
      "unit": "V/µs",
      "conditions": "G = +2, 2V output step"
    },
    "SR_G____2__4V_output_step": {
      "parameter": "Slew Rate",
      "min": null,
      "typ": 130,
      "max": null,
      "unit": "V/µs",
      "conditions": "G = +2, 4V output step"
    },
    "tr/tf": {
      "parameter": "Rise-and-Fall Time",
      "min": null,
      "typ": 4,
      "max": null,
      "unit": "ns",
      "conditions": "G = +2, VOUT = 0.2VP-P, 10% to 90%"
    },
    "ts": {
      "parameter": "Settling Time to 0.1%",
      "min": null,
      "typ": 58,
      "max": null,
      "unit": "ns",
      "conditions": "G = +2, 2V output step"
    },
    "en": {
      "parameter": "Input Voltage Noise Density",
      "min": null,
      "typ": 8.1,
      "max": null,
      "unit": "nV/√Hz",
      "conditions": "f = 1MHz"
    },
    "DG": {
      "parameter": "Differential Gain Error (NTSC)",
      "min": null,
      "typ": 0.03,
      "max": null,
      "unit": "%",
      "conditions": "G = +2, RL = 150Ω"
    },
    "DP": {
      "parameter": "Differential Phase Error (NTSC)",
      "min": null,
      "typ": 0.08,
      "max": null,
      "unit": "degree",
      "conditions": "G = +2, RL = 150Ω"
    },
    "VOS": {
      "parameter": "Input Offset Voltage",
      "min": null,
      "typ": null,
      "max": 9.8,
      "unit": "mV",
      "conditions": null
    },
    "ΔVOS/ΔT": {
      "parameter": "Input Offset Voltage Drift",
      "min": null,
      "typ": 4.4,
      "max": null,
      "unit": "µV/°C",
      "conditions": null
    },
    "IB": {
      "parameter": "Input Bias Current",
      "min": null,
      "typ": 6,
      "max": null,
      "unit": "pA",
      "conditions": null
    },
    "IOS": {
      "parameter": "Input Offset Current",
      "min": null,
      "typ": 2,
      "max": null,
      "unit": "pA",
      "conditions": null
    },
    "AOL": {
      "parameter": "Open-Loop Gain",
      "min": 75,
      "typ": 80,
      "max": null,
      "unit": "dB",
      "conditions": "VOUT = 0.3V to 4.7V, RL = 150Ω"
    },
    "AOL_VOUT___0_3V_to_4_7V__RL___150": {
      "parameter": "Open-Loop Gain",
      "min": 73,
      "typ": null,
      "max": null,
      "unit": "dB",
      "conditions": "VOUT = 0.3V to 4.7V, RL = 150Ω"
    },
    "AOL_VOUT___0_2V_to_4_8V__RL___1k": {
      "parameter": "Open-Loop Gain",
      "min": 80,
      "typ": null,
      "max": null,
      "unit": "dB",
      "conditions": "VOUT = 0.2V to 4.8V, RL = 1kΩ"
    },
    "VCM": {
      "parameter": "Input Common Mode Voltage Range",
      "min": -0.2,
      "typ": null,
      "max": 3.8,
      "unit": "V",
      "conditions": null
    },
    "CMRR": {
      "parameter": "Common Mode Rejection Ratio",
      "min": 66,
      "typ": 80,
      "max": null,
      "unit": "dB",
      "conditions": "VCM = -0.1V to 3.5V"
    },
    "CMRR_VCM____0_1V_to_3_5V": {
      "parameter": "Common Mode Rejection Ratio",
      "min": 62,
      "typ": null,
      "max": null,
      "unit": "dB",
      "conditions": "VCM = -0.1V to 3.5V"
    },
    "IO": {
      "parameter": "Output Current",
      "min": 84,
      "typ": null,
      "max": null,
      "unit": "mA",
      "conditions": null
    },
    "ZO": {
      "parameter": "Closed-Loop Output Impedance",
      "min": null,
      "typ": 0.08,
      "max": null,
      "unit": "Ω",
      "conditions": "f < 100kHz"
    },
    "tON": {
      "parameter": "Turn-On Time",
      "min": null,
      "typ": 236,
      "max": null,
      "unit": "ns",
      "conditions": null
    },
    "tOFF": {
      "parameter": "Turn-Off Time",
      "min": null,
      "typ": 52,
      "max": null,
      "unit": "ns",
      "conditions": null
    },
    "IOFF": {
      "parameter": "Output Leakage Current",
      "min": null,
      "typ": 50,
      "max": null,
      "unit": "pA",
      "conditions": "DISABLE = 0V, VS = 5V, VOUT = 5V"
    },
    "VS": {
      "parameter": "Operating Voltage Range",
      "min": 2.7,
      "typ": null,
      "max": 5.5,
      "unit": "V",
      "conditions": null
    },
    "IQ": {
      "parameter": "Quiescent Current",
      "min": null,
      "typ": null,
      "max": 4,
      "unit": "mA",
      "conditions": null
    },
    "IQ(SHDN)": {
      "parameter": "Supply Current when Disabled",
      "min": null,
      "typ": null,
      "max": 137,
      "unit": "µA",
      "conditions": null
    },
    "PSRR": {
      "parameter": "Power Supply Rejection Ratio",
      "min": 67,
      "typ": 80,
      "max": null,
      "unit": "dB",
      "conditions": "VS = 2.7V to 5.5V, VCM = (-VS) + 0.5V"
    },
    "PSRR_VS___2_7V_to_5_5V__VCM_____VS": {
      "parameter": "Power Supply Rejection Ratio",
      "min": 62,
      "typ": null,
      "max": null,
      "unit": "dB",
      "conditions": "VS = 2.7V to 5.5V, VCM = (-VS) + 0.5V"
    }
  },
  "drc_hints": {
    "vin_abs_max": {
      "value": 6,
      "unit": "V"
    },
    "vin_operating": {
      "min": -0.2,
      "max": 3.8,
      "unit": "V"
    },
    "iout_max": {
      "min": 100,
      "typ": 130,
      "unit": "mA"
    },
    "iq": {
      "typ": 2.3,
      "max": 3.2,
      "unit": "mA"
    }
  },
  "thermal": {}
}
