{
  "_schema": "selection-profile/1.0",
  "mpn": "SGM2053",
  "manufacturer": "SGMICRO",
  "category": "LDO",
  "description": "500mA, Ultra-Low Dropout, Low Power, RF Linear Regulator",
  "key_specs": {
    "input_voltage": {
      "min": 1.5,
      "max": 5.5,
      "unit": "V"
    },
    "output_current": {
      "min": 550,
      "typ": 980,
      "unit": "mA"
    },
    "quiescent_current": {
      "typ": 17,
      "max": 40,
      "unit": "µA"
    },
    "shutdown_current": {
      "typ": 0.03,
      "max": 2,
      "unit": "µA"
    },
    "reference_voltage": {
      "min": 0.792,
      "typ": 0.8,
      "max": 0.808,
      "unit": "V"
    },
    "dropout_voltage": {
      "typ": 440,
      "max": 500,
      "unit": "mV"
    },
    "output_voltage_accuracy": {
      "min": -1,
      "max": 1,
      "unit": "%"
    },
    "thermal_shutdown": {
      "typ": 160,
      "unit": "°C"
    },
    "output_voltage": {
      "min": -1,
      "max": 1,
      "unit": "%"
    },
    "enable_threshold": {
      "min": 0.7,
      "unit": "V"
    }
  },
  "operating_conditions": {
    "vin_range": [
      1.5,
      5.5
    ],
    "vout_range": [
      -1,
      1
    ],
    "iout_max": 980
  },
  "packages": [
    "SOT-23-6"
  ],
  "pin_count": 6,
  "thermal": {
    "theta_ja": {
      "max": 196,
      "unit": "°C/W"
    },
    "theta_jb": {
      "max": 61,
      "unit": "°C/W"
    },
    "theta_jc": {
      "max": 81,
      "unit": "°C/W"
    }
  },
  "features": [],
  "source_file": "SGM2053.json"
}
