{
  "_schema": "selection-profile/1.0",
  "mpn": "TS12A12511",
  "manufacturer": "Texas Instruments",
  "category": "Switch",
  "description": "5Ω Single-Channel SPDT Analog Switch with Negative Signal Capability",
  "key_specs": {
    "input_voltage": {
      "min": 0,
      "max": 0.8,
      "unit": "V"
    },
    "enable_threshold": {
      "min": 2.4,
      "unit": "V"
    },
    "input_voltage_abs_max": {
      "max": 13,
      "unit": "V"
    }
  },
  "operating_conditions": {
    "vin_range": [
      0,
      0.8
    ],
    "temp_range": [
      -40,
      85
    ],
    "temp_unit": "C",
    "tj_max": 150
  },
  "packages": [
    "SOT-23-8",
    "VSSOP-8",
    "WSON-8"
  ],
  "pin_count": 9,
  "thermal": {},
  "features": [],
  "source_file": "TS12A12511.json"
}
