{
  "_schema": "selection-profile/1.0",
  "mpn": "XC6120 Series",
  "manufacturer": "TOREX",
  "category": "Voltage Detector",
  "description": "Highly Accurate, Ultra Small, Low Power Consumption Voltage Detector",
  "key_specs": {
    "input_voltage": {
      "min": 0.7,
      "max": 6.0,
      "unit": "V"
    },
    "output_current": {
      "min": 0.09,
      "typ": 0.57,
      "unit": "mA"
    },
    "soft_start_time": {
      "typ": 0.5,
      "max": 1.4,
      "unit": "uA"
    },
    "input_voltage_abs_max": {
      "max": 7.0,
      "unit": "V"
    }
  },
  "operating_conditions": {
    "vin_range": [
      0.7,
      6.0
    ],
    "iout_max": 0.57,
    "temp_range": [
      -40,
      85
    ],
    "temp_unit": "C"
  },
  "packages": [
    "SOT-25",
    "SSOT-24",
    "USP-3"
  ],
  "pin_count": 5,
  "thermal": {
    "power_dissipation": {
      "max": 120,
      "unit": "mW"
    },
    "power_dissipation_40mm_x_40mm_Standard_board": {
      "max": 1000,
      "unit": "mW"
    },
    "power_dissipation_Power_Dissipation__SSOT_24": {
      "max": 150,
      "unit": "mW"
    },
    "power_dissipation_40mm_x_40mm_Standard_board_dup": {
      "max": 500,
      "unit": "mW"
    },
    "power_dissipation_Power_Dissipation__SOT_25": {
      "max": 250,
      "unit": "mW"
    },
    "power_dissipation_40mm_x_40mm_Standard_board_dup_dup": {
      "max": 600,
      "unit": "mW"
    }
  },
  "features": [],
  "source_file": "XC6120_Series.json"
}
